up2cos.py
up2cos-0.1.4.dist-info/LICENSE
up2cos-0.1.4.dist-info/METADATA
up2cos-0.1.4.dist-info/WHEEL
up2cos-0.1.4.dist-info/top_level.txt
up2cos-0.1.4.dist-info/RECORD
