Metadata-Version: 2.1
Name: up2cos
Version: 0.1.4
Summary: Save uploaded pictures in Tencent COS.
Home-page: https://github.com/staugur/picbed-up2cos
Author: staugur
Author-email: staugur@saintic.com
License: BSD 3-Clause
Platform: UNKNOWN
Requires-Dist: cos-python-sdk-v5 (>1.6.0)
